{"installations":19293,"repositories":960020,"popular":[{"id":949404,"login":"overtrue","stars":29478},{"id":1221302,"login":"hemanth","stars":26715},{"id":34214477,"login":"spicetify","stars":20755},{"id":26765889,"login":"moul","stars":12924},{"id":13453857,"login":"ameizi","stars":11916},{"id":6275018,"login":"bestony","stars":10664},{"id":5124183,"login":"guanguans","stars":10168},{"id":38120716,"login":"major","stars":10139},{"id":30561096,"login":"nefarius","stars":9923},{"id":15116260,"login":"kenzok8","stars":8003}]}
