{"installations":18726,"repositories":910974,"popular":[{"id":949404,"login":"overtrue","stars":29312},{"id":1221302,"login":"hemanth","stars":26637},{"id":34214477,"login":"spicetify","stars":20259},{"id":26765889,"login":"moul","stars":12752},{"id":13453857,"login":"ameizi","stars":11903},{"id":6275018,"login":"bestony","stars":10587},{"id":5124183,"login":"guanguans","stars":10034},{"id":38120716,"login":"major","stars":10032},{"id":30561096,"login":"nefarius","stars":9516},{"id":15116260,"login":"kenzok8","stars":7644}]}
