{"installations":19541,"repositories":969664,"popular":[{"id":949404,"login":"overtrue","stars":29576},{"id":1221302,"login":"hemanth","stars":26755},{"id":34214477,"login":"spicetify","stars":20976},{"id":26765889,"login":"moul","stars":12979},{"id":13453857,"login":"ameizi","stars":11927},{"id":6275018,"login":"bestony","stars":10702},{"id":5124183,"login":"guanguans","stars":10306},{"id":38120716,"login":"major","stars":10191},{"id":30561096,"login":"nefarius","stars":10066},{"id":15116260,"login":"kenzok8","stars":8219}]}
