{"installations":23705,"repositories":1253908,"popular":[{"id":1221302,"login":"hemanth","stars":27926},{"id":34214477,"login":"spicetify","stars":27739},{"id":26765889,"login":"moul","stars":14299},{"id":46036340,"login":"imsyy","stars":13465},{"id":30561096,"login":"nefarius","stars":13305},{"id":13453857,"login":"v5tech","stars":12225},{"id":5124183,"login":"guanguans","stars":11962},{"id":6275018,"login":"bestony","stars":11576},{"id":38120716,"login":"major","stars":11125},{"id":15116260,"login":"kenzok8","stars":11020}]}
